LICENSE
README.md
setup.cfg
setup.py
tests/test_unit_xfoil.py
xfoil_wrapper/__init__.py
xfoil_wrapper/utils.py
xfoil_wrapper/xfoil.py
xfoil_wrapper.egg-info/PKG-INFO
xfoil_wrapper.egg-info/SOURCES.txt
xfoil_wrapper.egg-info/dependency_links.txt
xfoil_wrapper.egg-info/requires.txt
xfoil_wrapper.egg-info/top_level.txt
xfoil_wrapper/__exe__/__init__.py
xfoil_wrapper/__exe__/pplot.exe
xfoil_wrapper/__exe__/pxplot.exe
xfoil_wrapper/__exe__/xfoil.exe