Metadata-Version: 2.1
Name: xfoil-wrapper
Version: 0.1.0
Summary: Wrapper for XFoil 6.99 by Marc Drela in Windows machine.
Home-page: https://github.com/open-foil
Download-URL: https://github.com/open-foil/xfoil-wrapper/archive/refs/tags/v0.1.0.tar.gz
Author: OpenFoil
Author-email: openfoil.project@gmail.com
License: MIT
Keywords: xfoil,wrapper,aerodynamics,airfoil
Classifier: Development Status :: 3 - Alpha
Classifier: Intended Audience :: Developers
Classifier: Topic :: Software Development :: Build Tools
Classifier: License :: OSI Approved :: MIT License
Classifier: Programming Language :: Python :: 3
Classifier: Programming Language :: Python :: 3.9
Classifier: Programming Language :: Python :: 3.10
Classifier: Programming Language :: Python :: 3.11
License-File: LICENSE
